pyopenjtalk_prebuilt-0.3.0.dist-info/LICENSE.md
pyopenjtalk_prebuilt-0.3.0.dist-info/RECORD
pyopenjtalk_prebuilt-0.3.0.dist-info/WHEEL
pyopenjtalk_prebuilt-0.3.0.dist-info/top_level.txt
pyopenjtalk_prebuilt-0.3.0.dist-info/METADATA
pyopenjtalk/version.py
pyopenjtalk/htsengine.cpython-38-darwin.so
pyopenjtalk/__init__.py
pyopenjtalk/utils.py
pyopenjtalk/openjtalk.cpython-38-darwin.so
pyopenjtalk/htsvoice/LICENSE_mei_normal.htsvoice
pyopenjtalk/htsvoice/README.md
pyopenjtalk/htsvoice/mei_normal.htsvoice
